elo_system.py
python_elo_system-3.0.2.dist-info/METADATA
python_elo_system-3.0.2.dist-info/WHEEL
test_elo_system.py
python_elo_system-3.0.2.dist-info/RECORD
