Metadata-Version: 2.1
Name: python-elo-system
Version: 3.0.2
Summary: Yet another Python Implementation of the Elo rating system.
Keywords: elo
Author-Email: Kraktoos <kraktoos@gmail.com>
Maintainer-Email: Samuel Wu <twopizza9621536@gmail.com>
License: MIT
Classifier: License :: OSI Approved :: MIT License
Classifier: Programming Language :: Python
Classifier: Programming Language :: Python :: 3.10
Classifier: Programming Language :: Python :: 3.11
Classifier: Programming Language :: Python :: 3.12
Project-URL: Documentation, https://github.com/TwoPizza9621536/python-elo-system#readme
Project-URL: Issues, https://github.com/TwoPizza9621536/python-elo-system/issues
Project-URL: Source, https://github.com/TwoPizza9621536/python-elo-system
Requires-Python: >=3.10
Requires-Dist: attrs>=23.2.0
